termcolor_util/__init__.py
termcolor_util/__main__.py
termcolor_util/py.typed
termcolor_util-2022.11.1.dist-info/WHEEL
termcolor_util-2022.11.1.dist-info/METADATA
termcolor_util-2022.11.1.dist-info/RECORD
