Metadata-Version: 2.1
Name: termcolor-util
Version: 2022.11.1
Summary: wrapper functions over termcolor
License: BSD
Author: Bogdan Mustiata
Author-email: bogdan.mustiata@gmail.com
Requires-Python: >=3.5,<4.0
Classifier: License :: Other/Proprietary License
Classifier: Programming Language :: Python :: 3
Classifier: Programming Language :: Python :: 3.5
Classifier: Programming Language :: Python :: 3.6
Classifier: Programming Language :: Python :: 3.7
Classifier: Programming Language :: Python :: 3.8
Classifier: Programming Language :: Python :: 3.9
Classifier: Programming Language :: Python :: 3.10
Classifier: Programming Language :: Python :: 3.11
Requires-Dist: termcolor (>=2.1.0,<3.0.0)
